{"trial_id": "0003", "hyperparameters": {"space": [{"class_name": "Choice", "config": {"name": "learning_rate", "default": 0.001, "conditions": [], "values": [0.001, 0.01, 0.1], "ordered": true}}, {"class_name": "Choice", "config": {"name": "batch_size", "default": 32, "conditions": [], "values": [32, 64, 128], "ordered": true}}], "values": {"learning_rate": 0.01, "batch_size": 32}}, "metrics": {"metrics": {"loss": {"direction": "min", "observations": [{"value": [0.1261962503194809], "step": 9}]}, "accuracy": {"direction": "max", "observations": [{"value": [0.9617484211921692], "step": 9}]}, "val_loss": {"direction": "min", "observations": [{"value": [0.10243651270866394], "step": 9}]}, "val_accuracy": {"direction": "max", "observations": [{"value": [0.9683333039283752], "step": 9}]}}}, "score": 0.10243651270866394, "best_step": 9, "status": "COMPLETED", "message": null}